<annotation verified="yes">
	<folder>carros</folder>
	<filename>00272.jpg</filename>
	<path>C:\Users\sena\Desktop\Paquetes apps\carros\00272.jpg</path>
	<source>
		<database>Unknown</database>
	</source>
	<size>
		<width>600</width>
		<height>331</height>
		<depth>3</depth>
	</size>
	<segmented>0</segmented>
	<object>
		<name>Carro</name>
		<pose>Unspecified</pose>
		<truncated>0</truncated>
		<difficult>0</difficult>
		<bndbox>
			<xmin>19</xmin>
			<ymin>21</ymin>
			<xmax>589</xmax>
			<ymax>323</ymax>
		</bndbox>
	</object>
</annotation>
